{"version":3,"kind":"Article","sha256":"4cc07b37657b7e7ca2f697a0b7814a4f1643e45414f18b1affcb107f917efed3","slug":"participant-data-analysis.mouse-tracking-data.mouse-tracking-data","location":"/participant_data_analysis/mouse_tracking_data/mouse_tracking_data.md","dependencies":[],"frontmatter":{"keywords":["Uncertainty","Quantification","Reinforcement Learning","Bayesian Inference","Active Inference"],"numbering":{"title":{"offset":2}},"exports":[{"format":"md","filename":"mouse_tracking_data.md","url":"/tambi-website//build/mouse_tracking_data-a0469a8517aed3f9b8df5b90673acd32.md"}]},"mdast":{"type":"root","children":[{"type":"block","children":[{"type":"paragraph","position":{"start":{"line":1,"column":1},"end":{"line":1,"column":1}},"children":[{"type":"text","value":"tba","position":{"start":{"line":1,"column":1},"end":{"line":1,"column":1}},"key":"mbM3ajSGl2"}],"key":"qEWcMJnMZH"}],"key":"CQFzeVz7E4"}],"key":"ZMubpTbs6Y"},"references":{"cite":{"order":[],"data":{}}},"footer":{"navigation":{"prev":{"title":"Pupil Data Analysis","url":"/participant-data-analysis/pupil-data/pupil-data-analysis","group":"The Pupil Data"},"next":{"title":"Eye Gaze And Mouse Movement Synchronization","url":"/participant-data-analysis/eye-mouse-sync/eye-gaze-and-mouse-movement-synchronization","group":"Eye Gaze and Mouse Movement Synchronization and Analysis"}}},"domain":"http://localhost:3000"}