{"version":3,"kind":"Article","sha256":"a77fd77091f84dc5a844b0b6c468d005c9c9cbea688c9b69535be630bfa32be8","slug":"simulation-models.environment-obs-action-space","location":"/simulation_models/environment_obs_action_space.md","dependencies":[],"frontmatter":{"title":"The Environment","content_includes_title":false,"keywords":["Uncertainty","Quantification","Reinforcement Learning","Bayesian Inference","Active Inference"],"numbering":{"title":{"offset":2}},"exports":[{"format":"md","filename":"environment_obs_action_space.md","url":"/tambi-website//build/environment_obs_acti-cc2ae79a5789e07a7b17c0a9bf27aa58.md"}]},"mdast":{"type":"root","children":[{"type":"block","children":[{"type":"heading","depth":2,"position":{"start":{"line":3,"column":1},"end":{"line":3,"column":1}},"children":[{"type":"text","value":"The Observations","position":{"start":{"line":3,"column":1},"end":{"line":3,"column":1}},"key":"j9MEDhGgnR"}],"identifier":"the-observations","label":"The Observations","html_id":"the-observations","implicit":true,"key":"IrjrXZ4ZiU"},{"type":"heading","depth":2,"position":{"start":{"line":5,"column":1},"end":{"line":5,"column":1}},"children":[{"type":"text","value":"The Action Space","position":{"start":{"line":5,"column":1},"end":{"line":5,"column":1}},"key":"t0fPOY7iqH"}],"identifier":"the-action-space","label":"The Action Space","html_id":"the-action-space","implicit":true,"key":"sJONOWS2N2"}],"key":"wnE75C5GGo"}],"key":"eIUidvIh2o"},"references":{"cite":{"order":[],"data":{}}},"footer":{"navigation":{"prev":{"title":"The General Architecture","short_title":"The General Architecture (Core Model Components for All Models)","url":"/simulation-models/the-general-architecture","group":"TAMBI - Documentation"},"next":{"title":"The Rao Blackwell Particle Filter","url":"/simulation-models/the-rao-blackwell-particle-filter","group":"TAMBI - Documentation"}}},"domain":"http://localhost:3000"}